{
  "shapes": [
    {
      "label": "পৃৃথিবীতে",
      "points": [
        [
          207.909090909091,
          43.36363636363636
        ],
        [
          648.8181818181818,
          316.09090909090907
        ]
      ]
    },
    {
      "label": "কোনো",
      "points": [
        [
          662.4545454545455,
          102.45454545454547
        ],
        [
          926.090909090909,
          297.90909090909093
        ]
      ]
    },
    {
      "label": "বস্তুকেই",
      "points": [
        [
          944.2727272727273,
          20.636363636363633
        ],
        [
          1330.6363636363635,
          302.45454545454544
        ]
      ]
    },
    {
      "label": "তুচ্ছজ্ঞান",
      "points": [
        [
          1371.5454545454545,
          75.18181818181819
        ],
        [
          1794.2727272727275,
          279.72727272727275
        ]
      ]
    },
    {
      "label": "করা",
      "points": [
        [
          1857.909090909091,
          93.36363636363637
        ],
        [
          2071.5454545454545,
          252.45454545454544
        ]
      ]
    },
    {
      "label": "উচিত",
      "points": [
        [
          2085.181818181818,
          25.181818181818187
        ],
        [
          2335.181818181818,
          243.36363636363637
        ]
      ]
    },
    {
      "label": "নয়",
      "points": [
        [
          2335.181818181818,
          66.0909090909091
        ],
        [
          2503.3636363636365,
          216.09090909090907
        ]
      ]
    },
    {
      "label": "।",
      "points": [
        [
          2503.3636363636365,
          47.90909090909091
        ],
        [
          2562.4545454545455,
          225.1818181818182
        ]
      ]
    },
    {
      "label": "অতি",
      "points": [
        [
          135.18181818181824,
          402.45454545454544
        ],
        [
          462.4545454545455,
          634.2727272727273
        ]
      ]
    },
    {
      "label": "তুচ্ছ",
      "points": [
        [
          494.27272727272725,
          466.09090909090907
        ],
        [
          721.5454545454545,
          657.0
        ]
      ]
    },
    {
      "label": "বস্তুর",
      "points": [
        [
          762.4545454545455,
          429.72727272727275
        ],
        [
          1089.7272727272725,
          638.8181818181819
        ]
      ]
    },
    {
      "label": "মধ্যেও",
      "points": [
        [
          1162.4545454545455,
          379.72727272727275
        ],
        [
          1585.181818181818,
          625.1818181818181
        ]
      ]
    },
    {
      "label": "হয়তো",
      "points": [
        [
          1639.7272727272725,
          384.27272727272725
        ],
        [
          1962.4545454545455,
          597.9090909090909
        ]
      ]
    },
    {
      "label": "লুকিয়ে",
      "points": [
        [
          1980.6363636363635,
          320.6363636363636
        ],
        [
          2371.5454545454545,
          625.1818181818181
        ]
      ]
    },
    {
      "label": "থাকতে",
      "points": [
        [
          112.4545454545455,
          707.0
        ],
        [
          503.36363636363626,
          916.0909090909091
        ]
      ]
    },
    {
      "label": "পারে",
      "points": [
        [
          548.8181818181818,
          702.4545454545455
        ],
        [
          817.0,
          920.6363636363636
        ]
      ]
    },
    {
      "label": "বিশাল",
      "points": [
        [
          835.1818181818182,
          675.1818181818181
        ],
        [
          1153.3636363636365,
          902.4545454545455
        ]
      ]
    },
    {
      "label": "কোনো",
      "points": [
        [
          1217.0,
          693.3636363636364
        ],
        [
          1530.6363636363635,
          907.0
        ]
      ]
    },
    {
      "label": "সম্ভাবনা",
      "points": [
        [
          1567.0,
          629.7272727272727
        ],
        [
          2094.2727272727275,
          820.6363636363636
        ]
      ]
    },
    {
      "label": "।",
      "points": [
        [
          2139.7272727272725,
          638.8181818181819
        ],
        [
          2221.5454545454545,
          797.9090909090909
        ]
      ]
    },
    {
      "label": "বস্তুর",
      "points": [
        [
          35.181818181818244,
          1002.4545454545455
        ],
        [
          348.81818181818176,
          1211.5454545454545
        ]
      ]
    },
    {
      "label": "প্রয়োজন",
      "points": [
        [
          389.72727272727275,
          993.3636363636363
        ],
        [
          776.090909090909,
          1170.6363636363637
        ]
      ]
    },
    {
      "label": "বিভিন্ন",
      "points": [
        [
          830.6363636363637,
          920.6363636363636
        ],
        [
          1103.3636363636365,
          1188.8181818181818
        ]
      ]
    },
    {
      "label": "সময়ে",
      "points": [
        [
          1176.090909090909,
          938.8181818181819
        ],
        [
          1539.7272727272725,
          1152.4545454545455
        ]
      ]
    },
    {
      "label": "বিভিন্নভাবে",
      "points": [
        [
          1571.5454545454545,
          866.0909090909091
        ],
        [
          2112.4545454545455,
          1129.7272727272727
        ]
      ]
    },
    {
      "label": "পরিবর্তিত",
      "points": [
        [
          2139.7272727272725,
          802.4545454545455
        ],
        [
          2662.4545454545455,
          1107.0
        ]
      ]
    },
    {
      "label": "হয়",
      "points": [
        [
          48.818181818181756,
          1238.8181818181818
        ],
        [
          289.72727272727275,
          1429.7272727272727
        ]
      ]
    },
    {
      "label": "।",
      "points": [
        [
          282.23076923076917,
          1265.3846153846152
        ],
        [
          351.46153846153845,
          1411.5384615384614
        ]
      ]
    },
    {
      "label": "কাজেই",
      "points": [
        [
          389.9230769230769,
          1169.2307692307693
        ],
        [
          813.0,
          1430.7692307692307
        ]
      ]
    },
    {
      "label": "বস্তুর",
      "points": [
        [
          889.9230769230769,
          1226.923076923077
        ],
        [
          1197.6153846153845,
          1426.923076923077
        ]
      ]
    },
    {
      "label": "স্বাভাবিক",
      "points": [
        [
          1243.7692307692307,
          1146.1538461538462
        ],
        [
          1716.8461538461538,
          1411.5384615384614
        ]
      ]
    },
    {
      "label": "অন্তর্নিহিক",
      "points": [
        [
          1797.6153846153848,
          1123.076923076923
        ],
        [
          2413.0,
          1373.076923076923
        ]
      ]
    },
    {
      "label": "গুনের",
      "points": [
        [
          28.38461538461536,
          1515.3846153846152
        ],
        [
          328.38461538461536,
          1707.6923076923076
        ]
      ]
    },
    {
      "label": "কথা",
      "points": [
        [
          424.53846153846143,
          1526.923076923077
        ],
        [
          705.3076923076922,
          1673.076923076923
        ]
      ]
    },
    {
      "label": "চিন্তা",
      "points": [
        [
          782.2307692307693,
          1461.5384615384614
        ],
        [
          1020.6923076923076,
          1715.3846153846152
        ]
      ]
    },
    {
      "label": "করে",
      "points": [
        [
          1101.4615384615383,
          1519.2307692307693
        ],
        [
          1347.6153846153845,
          1707.6923076923076
        ]
      ]
    },
    {
      "label": "সব",
      "points": [
        [
          1413.0,
          1450.0
        ],
        [
          1666.8461538461538,
          1646.1538461538462
        ]
      ]
    },
    {
      "label": "জিনিসকেই",
      "points": [
        [
          1728.3846153846152,
          1369.2307692307693
        ],
        [
          2351.4615384615386,
          1676.923076923077
        ]
      ]
    },
    {
      "label": "পরীক্ষা",
      "points": [
        [
          28.38461538461536,
          1703.8461538461538
        ],
        [
          443.7692307692307,
          1992.3076923076922
        ]
      ]
    },
    {
      "label": "নিরীক্ষা",
      "points": [
        [
          455.3076923076924,
          1707.6923076923076
        ],
        [
          886.0769230769231,
          2015.3846153846152
        ]
      ]
    },
    {
      "label": "করে",
      "points": [
        [
          939.9230769230769,
          1773.076923076923
        ],
        [
          1193.7692307692307,
          1988.4615384615383
        ]
      ]
    },
    {
      "label": "দেখা",
      "points": [
        [
          1220.6923076923076,
          1776.923076923077
        ],
        [
          1539.9230769230767,
          1976.923076923077
        ]
      ]
    },
    {
      "label": "আবশ্যক",
      "points": [
        [
          1578.3846153846152,
          1765.3846153846152
        ],
        [
          2039.9230769230767,
          1965.3846153846152
        ]
      ]
    },
    {
      "label": "।",
      "points": [
        [
          2047.6153846153843,
          1800.0
        ],
        [
          2109.153846153846,
          1938.4615384615383
        ]
      ]
    },
    {
      "label": "অতি",
      "points": [
        [
          2124.5384615384614,
          1696.1538461538462
        ],
        [
          2474.5384615384614,
          1946.1538461538462
        ]
      ]
    },
    {
      "label": "ক্ষুদ্র",
      "points": [
        [
          16.84615384615381,
          2069.230769230769
        ],
        [
          297.6153846153845,
          2246.153846153846
        ]
      ]
    },
    {
      "label": "বা",
      "points": [
        [
          332.23076923076917,
          2092.3076923076924
        ],
        [
          497.6153846153845,
          2246.153846153846
        ]
      ]
    },
    {
      "label": "তুচ্ছ",
      "points": [
        [
          551.4615384615383,
          2069.230769230769
        ],
        [
          778.3846153846152,
          2257.6923076923076
        ]
      ]
    },
    {
      "label": "কোনো",
      "points": [
        [
          820.6923076923076,
          2065.3846153846152
        ],
        [
          1170.6923076923076,
          2261.5384615384614
        ]
      ]
    },
    {
      "label": "বস্তুর",
      "points": [
        [
          1224.5384615384614,
          2057.6923076923076
        ],
        [
          1551.4615384615386,
          2261.5384615384614
        ]
      ]
    },
    {
      "label": "মধ্যেও",
      "points": [
        [
          1613.0,
          2007.6923076923076
        ],
        [
          1993.7692307692305,
          2230.7692307692305
        ]
      ]
    },
    {
      "label": "লুকি",
      "points": [
        [
          2020.6923076923076,
          2000.0
        ],
        [
          2316.846153846154,
          2246.153846153846
        ]
      ]
    },
    {
      "label": "থাকতে",
      "points": [
        [
          20.692307692307622,
          2323.076923076923
        ],
        [
          432.2307692307693,
          2519.230769230769
        ]
      ]
    },
    {
      "label": "পারে",
      "points": [
        [
          463.0,
          2326.9230769230767
        ],
        [
          759.1538461538462,
          2530.7692307692305
        ]
      ]
    },
    {
      "label": "তমন",
      "points": [
        [
          839.9230769230769,
          2303.846153846154
        ],
        [
          1105.3076923076922,
          2496.153846153846
        ]
      ]
    },
    {
      "label": "কিছু",
      "points": [
        [
          1163.0,
          2300.0
        ],
        [
          1463.0,
          2538.4615384615386
        ]
      ]
    },
    {
      "label": "শক্তি",
      "points": [
        [
          1470.6923076923076,
          2276.9230769230767
        ],
        [
          1739.9230769230767,
          2538.4615384615386
        ]
      ]
    },
    {
      "label": "বা",
      "points": [
        [
          1755.3076923076924,
          2353.846153846154
        ],
        [
          1889.9230769230767,
          2503.846153846154
        ]
      ]
    },
    {
      "label": "সম্ভাবনা",
      "points": [
        [
          1947.6153846153843,
          2330.7692307692305
        ],
        [
          2463.0,
          2515.3846153846152
        ]
      ]
    },
    {
      "label": "যামানুষকে",
      "points": [
        [
          20.692307692307622,
          2561.5384615384614
        ],
        [
          566.8461538461538,
          2750.0
        ]
      ]
    },
    {
      "label": "পৌঁছে",
      "points": [
        [
          682.2307692307693,
          2526.9230769230767
        ],
        [
          1059.1538461538462,
          2761.5384615384614
        ]
      ]
    },
    {
      "label": "দিতে",
      "points": [
        [
          1086.076923076923,
          2557.6923076923076
        ],
        [
          1370.6923076923076,
          2765.3846153846152
        ]
      ]
    },
    {
      "label": "পারে",
      "points": [
        [
          1432.230769230769,
          2588.4615384615386
        ],
        [
          1716.8461538461538,
          2765.3846153846152
        ]
      ]
    },
    {
      "label": "উন্নতির",
      "points": [
        [
          1774.5384615384614,
          2546.153846153846
        ],
        [
          2178.3846153846152,
          2765.3846153846152
        ]
      ]
    },
    {
      "label": "চরম",
      "points": [
        [
          689.9230769230769,
          2784.6153846153843
        ],
        [
          966.8461538461538,
          2915.3846153846152
        ]
      ]
    },
    {
      "label": "শিখরে",
      "points": [
        [
          1016.8461538461538,
          2761.5384615384614
        ],
        [
          1413.0,
          2919.230769230769
        ]
      ]
    },
    {
      "label": "।",
      "points": [
        [
          1416.8461538461538,
          2780.7692307692305
        ],
        [
          1489.9230769230767,
          2919.230769230769
        ]
      ]
    }
  ],
  "imagePath": "201_16_1.jpg",
  "imageHeight": 2922,
  "imageWidth": 2664
}